{
  "keys": [
    {
      "key": "HAZZSCREENS",
      "plan": "vitalicio",
      "created_at": "2026-01-20T10:00:00Z",
      "expires_at": null,
      "active": true,
      "user": "admin@kernelbypass.com"
    },
    {
      "key": "ORGLAGARTO",
      "plan": "vitalicio",
      "created_at": "2026-07-01T10:00:00Z",
      "expires_at": null,
      "active": true,
      "user": "lagarto@email.com"
    },
    {
      "key": "BOSSALUGUELKEY",
      "plan": "vitalicio",
      "created_at": "2026-07-01T10:00:00Z",
      "expires_at": null,
      "active": true,
      "user": "bossaluguel@email.com"
    },
    {
      "key": "LAGARTO1D",
      "plan": "diario",
      "created_at": "2026-07-01T10:00:00Z",
      "expires_at": "2026-07-14T10:00:00Z",
      "active": true,
      "user": "lagarto1d@email.com"
    }
  ]
}
